<TODOLIST>
	<UITHEME STYLE = "GRADIENT">

		<COLOR NAME = "APPBACKDARK"		R = "195" G = "255" B = "195"/>
		<COLOR NAME = "APPBACKLIGHT"	R = "222" G = "255" B = "222"/>
		<COLOR NAME = "APPLINES"		R = "225" G = "255" B = "222"/>
		<COLOR NAME = "MENUBACK"		R = "225" G = "255" B = "225"/>
		<COLOR NAME = "TOOLBARDARK"		R = "195" G = "255" B = "195"/>
		<COLOR NAME = "TOOLBARLIGHT"	R = "222" G = "255" B = "222"/>
		<COLOR NAME = "STATUSBARDARK"	R = "195" G = "255" B = "195"/>
		<COLOR NAME = "STATUSBARLIGHT"	R = "222" G = "255" B = "222"/>
<!--
		<COLOR NAME = "" R = "" G = "" B = ""/>
		<COLOR NAME = "" R = "" G = "" B = ""/>
		<COLOR NAME = "" R = "" G = "" B = ""/>
-->
	</UITHEME>
</TODOLIST>

